{
  "directed": false,
  "multigraph": false,
  "graph": {},
  "nodes": [
    {
      "label": "eslint.config.js",
      "file_type": "code",
      "source_file": "eslint.config.js",
      "source_location": "L1",
      "id": "eslint_config_js",
      "community": 9,
      "norm_label": "eslint.config.js"
    },
    {
      "label": "package.json",
      "file_type": "code",
      "source_file": "package.json",
      "source_location": "L1",
      "id": "package_json",
      "community": 3,
      "norm_label": "package.json"
    },
    {
      "label": "name",
      "file_type": "code",
      "source_file": "package.json",
      "source_location": "L2",
      "id": "client_ayswariya_mahal_package_name",
      "community": 3,
      "norm_label": "name"
    },
    {
      "label": "private",
      "file_type": "code",
      "source_file": "package.json",
      "source_location": "L3",
      "id": "client_ayswariya_mahal_package_private",
      "community": 3,
      "norm_label": "private"
    },
    {
      "label": "version",
      "file_type": "code",
      "source_file": "package.json",
      "source_location": "L4",
      "id": "client_ayswariya_mahal_package_version",
      "community": 3,
      "norm_label": "version"
    },
    {
      "label": "type",
      "file_type": "code",
      "source_file": "package.json",
      "source_location": "L5",
      "id": "client_ayswariya_mahal_package_type",
      "community": 3,
      "norm_label": "type"
    },
    {
      "label": "scripts",
      "file_type": "code",
      "source_file": "package.json",
      "source_location": "L6",
      "id": "client_ayswariya_mahal_package_scripts",
      "community": 3,
      "norm_label": "scripts"
    },
    {
      "label": "dev",
      "file_type": "code",
      "source_file": "package.json",
      "source_location": "L7",
      "id": "client_ayswariya_mahal_package_scripts_dev",
      "community": 3,
      "norm_label": "dev"
    },
    {
      "label": "build",
      "file_type": "code",
      "source_file": "package.json",
      "source_location": "L8",
      "id": "client_ayswariya_mahal_package_scripts_build",
      "community": 3,
      "norm_label": "build"
    },
    {
      "label": "lint",
      "file_type": "code",
      "source_file": "package.json",
      "source_location": "L9",
      "id": "client_ayswariya_mahal_package_scripts_lint",
      "community": 3,
      "norm_label": "lint"
    },
    {
      "label": "preview",
      "file_type": "code",
      "source_file": "package.json",
      "source_location": "L10",
      "id": "client_ayswariya_mahal_package_scripts_preview",
      "community": 3,
      "norm_label": "preview"
    },
    {
      "label": "dependencies",
      "file_type": "code",
      "source_file": "package.json",
      "source_location": "L12",
      "id": "client_ayswariya_mahal_package_dependencies",
      "community": 5,
      "norm_label": "dependencies"
    },
    {
      "label": "clsx",
      "file_type": "code",
      "source_file": "package.json",
      "source_location": "L13",
      "id": "client_ayswariya_mahal_package_dependencies_clsx",
      "community": 5,
      "norm_label": "clsx"
    },
    {
      "label": "framer-motion",
      "file_type": "code",
      "source_file": "package.json",
      "source_location": "L14",
      "id": "client_ayswariya_mahal_package_dependencies_framer_motion",
      "community": 5,
      "norm_label": "framer-motion"
    },
    {
      "label": "gsap",
      "file_type": "code",
      "source_file": "package.json",
      "source_location": "L15",
      "id": "client_ayswariya_mahal_package_dependencies_gsap",
      "community": 5,
      "norm_label": "gsap"
    },
    {
      "label": "lucide-react",
      "file_type": "code",
      "source_file": "package.json",
      "source_location": "L16",
      "id": "client_ayswariya_mahal_package_dependencies_lucide_react",
      "community": 5,
      "norm_label": "lucide-react"
    },
    {
      "label": "react",
      "file_type": "code",
      "source_file": "package.json",
      "source_location": "L17",
      "id": "client_ayswariya_mahal_package_dependencies_react",
      "community": 5,
      "norm_label": "react"
    },
    {
      "label": "react-dom",
      "file_type": "code",
      "source_file": "package.json",
      "source_location": "L18",
      "id": "client_ayswariya_mahal_package_dependencies_react_dom",
      "community": 5,
      "norm_label": "react-dom"
    },
    {
      "label": "react-helmet-async",
      "file_type": "code",
      "source_file": "package.json",
      "source_location": "L19",
      "id": "client_ayswariya_mahal_package_dependencies_react_helmet_async",
      "community": 5,
      "norm_label": "react-helmet-async"
    },
    {
      "label": "react-router-dom",
      "file_type": "code",
      "source_file": "package.json",
      "source_location": "L20",
      "id": "client_ayswariya_mahal_package_dependencies_react_router_dom",
      "community": 5,
      "norm_label": "react-router-dom"
    },
    {
      "label": "sharp",
      "file_type": "code",
      "source_file": "package.json",
      "source_location": "L21",
      "id": "client_ayswariya_mahal_package_dependencies_sharp",
      "community": 5,
      "norm_label": "sharp"
    },
    {
      "label": "devDependencies",
      "file_type": "code",
      "source_file": "package.json",
      "source_location": "L23",
      "id": "client_ayswariya_mahal_package_devdependencies",
      "community": 2,
      "norm_label": "devdependencies"
    },
    {
      "label": "@eslint/js",
      "file_type": "code",
      "source_file": "package.json",
      "source_location": "L24",
      "id": "client_ayswariya_mahal_package_devdependencies_eslint_js",
      "community": 2,
      "norm_label": "@eslint/js"
    },
    {
      "label": "@tailwindcss/vite",
      "file_type": "code",
      "source_file": "package.json",
      "source_location": "L25",
      "id": "client_ayswariya_mahal_package_devdependencies_tailwindcss_vite",
      "community": 2,
      "norm_label": "@tailwindcss/vite"
    },
    {
      "label": "@types/react",
      "file_type": "code",
      "source_file": "package.json",
      "source_location": "L26",
      "id": "client_ayswariya_mahal_package_devdependencies_types_react",
      "community": 2,
      "norm_label": "@types/react"
    },
    {
      "label": "@types/react-dom",
      "file_type": "code",
      "source_file": "package.json",
      "source_location": "L27",
      "id": "client_ayswariya_mahal_package_devdependencies_types_react_dom",
      "community": 2,
      "norm_label": "@types/react-dom"
    },
    {
      "label": "@vitejs/plugin-react",
      "file_type": "code",
      "source_file": "package.json",
      "source_location": "L28",
      "id": "client_ayswariya_mahal_package_devdependencies_vitejs_plugin_react",
      "community": 2,
      "norm_label": "@vitejs/plugin-react"
    },
    {
      "label": "eslint",
      "file_type": "code",
      "source_file": "package.json",
      "source_location": "L29",
      "id": "client_ayswariya_mahal_package_devdependencies_eslint",
      "community": 2,
      "norm_label": "eslint"
    },
    {
      "label": "eslint-plugin-react-hooks",
      "file_type": "code",
      "source_file": "package.json",
      "source_location": "L30",
      "id": "client_ayswariya_mahal_package_devdependencies_eslint_plugin_react_hooks",
      "community": 2,
      "norm_label": "eslint-plugin-react-hooks"
    },
    {
      "label": "eslint-plugin-react-refresh",
      "file_type": "code",
      "source_file": "package.json",
      "source_location": "L31",
      "id": "client_ayswariya_mahal_package_devdependencies_eslint_plugin_react_refresh",
      "community": 2,
      "norm_label": "eslint-plugin-react-refresh"
    },
    {
      "label": "globals",
      "file_type": "code",
      "source_file": "package.json",
      "source_location": "L32",
      "id": "client_ayswariya_mahal_package_devdependencies_globals",
      "community": 2,
      "norm_label": "globals"
    },
    {
      "label": "tailwindcss",
      "file_type": "code",
      "source_file": "package.json",
      "source_location": "L33",
      "id": "client_ayswariya_mahal_package_devdependencies_tailwindcss",
      "community": 2,
      "norm_label": "tailwindcss"
    },
    {
      "label": "vite",
      "file_type": "code",
      "source_file": "package.json",
      "source_location": "L34",
      "id": "client_ayswariya_mahal_package_devdependencies_vite",
      "community": 2,
      "norm_label": "vite"
    },
    {
      "label": "vite.config.js",
      "file_type": "code",
      "source_file": "vite.config.js",
      "source_location": "L1",
      "id": "vite_config_js",
      "community": 10,
      "norm_label": "vite.config.js"
    },
    {
      "label": "App.jsx",
      "file_type": "code",
      "source_file": "src/App.jsx",
      "source_location": "L1",
      "id": "src_app_jsx",
      "community": 11,
      "norm_label": "app.jsx"
    },
    {
      "label": "Home",
      "file_type": "code",
      "source_file": "src/App.jsx",
      "source_location": "L9",
      "id": "src_app_home",
      "community": 11,
      "norm_label": "home"
    },
    {
      "label": "About",
      "file_type": "code",
      "source_file": "src/App.jsx",
      "source_location": "L10",
      "id": "src_app_about",
      "community": 11,
      "norm_label": "about"
    },
    {
      "label": "Facilities",
      "file_type": "code",
      "source_file": "src/App.jsx",
      "source_location": "L11",
      "id": "src_app_facilities",
      "community": 11,
      "norm_label": "facilities"
    },
    {
      "label": "Gallery",
      "file_type": "code",
      "source_file": "src/App.jsx",
      "source_location": "L12",
      "id": "src_app_gallery",
      "community": 11,
      "norm_label": "gallery"
    },
    {
      "label": "Contact",
      "file_type": "code",
      "source_file": "src/App.jsx",
      "source_location": "L13",
      "id": "src_app_contact",
      "community": 11,
      "norm_label": "contact"
    },
    {
      "label": "Reviews",
      "file_type": "code",
      "source_file": "src/App.jsx",
      "source_location": "L14",
      "id": "src_app_reviews",
      "community": 11,
      "norm_label": "reviews"
    },
    {
      "label": "PageLoader()",
      "file_type": "code",
      "source_file": "src/App.jsx",
      "source_location": "L17",
      "id": "src_app_pageloader",
      "community": 11,
      "norm_label": "pageloader()"
    },
    {
      "label": "App()",
      "file_type": "code",
      "source_file": "src/App.jsx",
      "source_location": "L23",
      "id": "src_app_app",
      "community": 11,
      "norm_label": "app()"
    },
    {
      "label": "main.jsx",
      "file_type": "code",
      "source_file": "src/main.jsx",
      "source_location": "L1",
      "id": "src_main_jsx",
      "community": 11,
      "norm_label": "main.jsx"
    },
    {
      "label": "FloatingEnvelope.jsx",
      "file_type": "code",
      "source_file": "src/components/common/FloatingEnvelope.jsx",
      "source_location": "L1",
      "id": "src_components_common_floatingenvelope_jsx",
      "community": 7,
      "norm_label": "floatingenvelope.jsx"
    },
    {
      "label": "QUOTES",
      "file_type": "code",
      "source_file": "src/components/common/FloatingEnvelope.jsx",
      "source_location": "L7",
      "id": "common_floatingenvelope_quotes",
      "community": 7,
      "norm_label": "quotes"
    },
    {
      "label": "FloatingEnvelope()",
      "file_type": "code",
      "source_file": "src/components/common/FloatingEnvelope.jsx",
      "source_location": "L14",
      "id": "common_floatingenvelope_floatingenvelope",
      "community": 7,
      "norm_label": "floatingenvelope()"
    },
    {
      "label": "Footer.jsx",
      "file_type": "code",
      "source_file": "src/components/common/Footer.jsx",
      "source_location": "L1",
      "id": "src_components_common_footer_jsx",
      "community": 12,
      "norm_label": "footer.jsx"
    },
    {
      "label": "Footer()",
      "file_type": "code",
      "source_file": "src/components/common/Footer.jsx",
      "source_location": "L5",
      "id": "common_footer_footer",
      "community": 12,
      "norm_label": "footer()"
    },
    {
      "label": "Navbar.jsx",
      "file_type": "code",
      "source_file": "src/components/common/Navbar.jsx",
      "source_location": "L1",
      "id": "src_components_common_navbar_jsx",
      "community": 7,
      "norm_label": "navbar.jsx"
    },
    {
      "label": "Navbar()",
      "file_type": "code",
      "source_file": "src/components/common/Navbar.jsx",
      "source_location": "L8",
      "id": "common_navbar_navbar",
      "community": 7,
      "norm_label": "navbar()"
    },
    {
      "label": "ScrollToTop.jsx",
      "file_type": "code",
      "source_file": "src/components/common/ScrollToTop.jsx",
      "source_location": "L1",
      "id": "src_components_common_scrolltotop_jsx",
      "community": 11,
      "norm_label": "scrolltotop.jsx"
    },
    {
      "label": "ScrollToTop()",
      "file_type": "code",
      "source_file": "src/components/common/ScrollToTop.jsx",
      "source_location": "L4",
      "id": "common_scrolltotop_scrolltotop",
      "community": 11,
      "norm_label": "scrolltotop()"
    },
    {
      "label": "SEO.jsx",
      "file_type": "code",
      "source_file": "src/components/common/SEO.jsx",
      "source_location": "L1",
      "id": "src_components_common_seo_jsx",
      "community": 1,
      "norm_label": "seo.jsx"
    },
    {
      "label": "SEO()",
      "file_type": "code",
      "source_file": "src/components/common/SEO.jsx",
      "source_location": "L4",
      "id": "common_seo_seo",
      "community": 1,
      "norm_label": "seo()"
    },
    {
      "label": "AboutPreview.jsx",
      "file_type": "code",
      "source_file": "src/components/home/AboutPreview.jsx",
      "source_location": "L1",
      "id": "src_components_home_aboutpreview_jsx",
      "community": 7,
      "norm_label": "aboutpreview.jsx"
    },
    {
      "label": "AboutPreview()",
      "file_type": "code",
      "source_file": "src/components/home/AboutPreview.jsx",
      "source_location": "L9",
      "id": "home_aboutpreview_aboutpreview",
      "community": 7,
      "norm_label": "aboutpreview()"
    },
    {
      "label": "ContactCTA.jsx",
      "file_type": "code",
      "source_file": "src/components/home/ContactCTA.jsx",
      "source_location": "L1",
      "id": "src_components_home_contactcta_jsx",
      "community": 7,
      "norm_label": "contactcta.jsx"
    },
    {
      "label": "ContactCTA()",
      "file_type": "code",
      "source_file": "src/components/home/ContactCTA.jsx",
      "source_location": "L4",
      "id": "home_contactcta_contactcta",
      "community": 7,
      "norm_label": "contactcta()"
    },
    {
      "label": "FacilitiesPreview.jsx",
      "file_type": "code",
      "source_file": "src/components/home/FacilitiesPreview.jsx",
      "source_location": "L1",
      "id": "src_components_home_facilitiespreview_jsx",
      "community": 0,
      "norm_label": "facilitiespreview.jsx"
    },
    {
      "label": "IMAGES",
      "file_type": "code",
      "source_file": "src/components/home/FacilitiesPreview.jsx",
      "source_location": "L14",
      "id": "home_facilitiespreview_images",
      "community": 0,
      "norm_label": "images"
    },
    {
      "label": "FacilitiesPreview()",
      "file_type": "code",
      "source_file": "src/components/home/FacilitiesPreview.jsx",
      "source_location": "L21",
      "id": "home_facilitiespreview_facilitiespreview",
      "community": 0,
      "norm_label": "facilitiespreview()"
    },
    {
      "label": "GalleryPreview.jsx",
      "file_type": "code",
      "source_file": "src/components/home/GalleryPreview.jsx",
      "source_location": "L1",
      "id": "src_components_home_gallerypreview_jsx",
      "community": 7,
      "norm_label": "gallerypreview.jsx"
    },
    {
      "label": "GalleryPreview()",
      "file_type": "code",
      "source_file": "src/components/home/GalleryPreview.jsx",
      "source_location": "L9",
      "id": "home_gallerypreview_gallerypreview",
      "community": 7,
      "norm_label": "gallerypreview()"
    },
    {
      "label": "GateExperience.jsx",
      "file_type": "code",
      "source_file": "src/components/home/GateExperience.jsx",
      "source_location": "L1",
      "id": "src_components_home_gateexperience_jsx",
      "community": 7,
      "norm_label": "gateexperience.jsx"
    },
    {
      "label": "GateExperience()",
      "file_type": "code",
      "source_file": "src/components/home/GateExperience.jsx",
      "source_location": "L11",
      "id": "home_gateexperience_gateexperience",
      "community": 7,
      "norm_label": "gateexperience()"
    },
    {
      "label": "Hero.jsx",
      "file_type": "code",
      "source_file": "src/components/home/Hero.jsx",
      "source_location": "L1",
      "id": "src_components_home_hero_jsx",
      "community": 8,
      "norm_label": "hero.jsx"
    },
    {
      "label": "Hero()",
      "file_type": "code",
      "source_file": "src/components/home/Hero.jsx",
      "source_location": "L6",
      "id": "home_hero_hero",
      "community": 8,
      "norm_label": "hero()"
    },
    {
      "label": "RoyalStatistics.jsx",
      "file_type": "code",
      "source_file": "src/components/home/RoyalStatistics.jsx",
      "source_location": "L1",
      "id": "src_components_home_royalstatistics_jsx",
      "community": 7,
      "norm_label": "royalstatistics.jsx"
    },
    {
      "label": "RoyalStatistics()",
      "file_type": "code",
      "source_file": "src/components/home/RoyalStatistics.jsx",
      "source_location": "L4",
      "id": "home_royalstatistics_royalstatistics",
      "community": 7,
      "norm_label": "royalstatistics()"
    },
    {
      "label": "site.js",
      "file_type": "code",
      "source_file": "src/config/site.js",
      "source_location": "L1",
      "id": "src_config_site_js",
      "community": 12,
      "norm_label": "site.js"
    },
    {
      "label": "siteConfig",
      "file_type": "code",
      "source_file": "src/config/site.js",
      "source_location": "L1",
      "id": "config_site_siteconfig",
      "community": 12,
      "norm_label": "siteconfig"
    },
    {
      "label": "EnquiryContext.jsx",
      "file_type": "code",
      "source_file": "src/context/EnquiryContext.jsx",
      "source_location": "L1",
      "id": "src_context_enquirycontext_jsx",
      "community": 7,
      "norm_label": "enquirycontext.jsx"
    },
    {
      "label": "EnquiryContext",
      "file_type": "code",
      "source_file": "src/context/EnquiryContext.jsx",
      "source_location": "L3",
      "id": "context_enquirycontext_enquirycontext",
      "community": 7,
      "norm_label": "enquirycontext"
    },
    {
      "label": "useEnquiry()",
      "file_type": "code",
      "source_file": "src/context/EnquiryContext.jsx",
      "source_location": "L5",
      "id": "context_enquirycontext_useenquiry",
      "community": 7,
      "norm_label": "useenquiry()"
    },
    {
      "label": "EnquiryProvider()",
      "file_type": "code",
      "source_file": "src/context/EnquiryContext.jsx",
      "source_location": "L7",
      "id": "context_enquirycontext_enquiryprovider",
      "community": 7,
      "norm_label": "enquiryprovider()"
    },
    {
      "label": "MainLayout.jsx",
      "file_type": "code",
      "source_file": "src/layouts/MainLayout.jsx",
      "source_location": "L1",
      "id": "src_layouts_mainlayout_jsx",
      "community": 7,
      "norm_label": "mainlayout.jsx"
    },
    {
      "label": "MainLayout()",
      "file_type": "code",
      "source_file": "src/layouts/MainLayout.jsx",
      "source_location": "L5",
      "id": "layouts_mainlayout_mainlayout",
      "community": 7,
      "norm_label": "mainlayout()"
    },
    {
      "label": "About.jsx",
      "file_type": "code",
      "source_file": "src/pages/About.jsx",
      "source_location": "L1",
      "id": "src_pages_about_jsx",
      "community": 1,
      "norm_label": "about.jsx"
    },
    {
      "label": "About()",
      "file_type": "code",
      "source_file": "src/pages/About.jsx",
      "source_location": "L8",
      "id": "pages_about_about",
      "community": 1,
      "norm_label": "about()"
    },
    {
      "label": "Contact.jsx",
      "file_type": "code",
      "source_file": "src/pages/Contact.jsx",
      "source_location": "L1",
      "id": "src_pages_contact_jsx",
      "community": 1,
      "norm_label": "contact.jsx"
    },
    {
      "label": "Contact()",
      "file_type": "code",
      "source_file": "src/pages/Contact.jsx",
      "source_location": "L7",
      "id": "pages_contact_contact",
      "community": 1,
      "norm_label": "contact()"
    },
    {
      "label": "Facilities.jsx",
      "file_type": "code",
      "source_file": "src/pages/Facilities.jsx",
      "source_location": "L1",
      "id": "src_pages_facilities_jsx",
      "community": 1,
      "norm_label": "facilities.jsx"
    },
    {
      "label": "Facilities",
      "file_type": "code",
      "source_file": "src/pages/Facilities.jsx",
      "source_location": "L60",
      "id": "pages_facilities_facilities",
      "community": 1,
      "norm_label": "facilities"
    },
    {
      "label": "Gallery.jsx",
      "file_type": "code",
      "source_file": "src/pages/Gallery.jsx",
      "source_location": "L1",
      "id": "src_pages_gallery_jsx",
      "community": 1,
      "norm_label": "gallery.jsx"
    },
    {
      "label": "galleryImages",
      "file_type": "code",
      "source_file": "src/pages/Gallery.jsx",
      "source_location": "L12",
      "id": "pages_gallery_galleryimages",
      "community": 1,
      "norm_label": "galleryimages"
    },
    {
      "label": "categories",
      "file_type": "code",
      "source_file": "src/pages/Gallery.jsx",
      "source_location": "L21",
      "id": "pages_gallery_categories",
      "community": 1,
      "norm_label": "categories"
    },
    {
      "label": "Gallery()",
      "file_type": "code",
      "source_file": "src/pages/Gallery.jsx",
      "source_location": "L23",
      "id": "pages_gallery_gallery",
      "community": 1,
      "norm_label": "gallery()"
    },
    {
      "label": "Home.jsx",
      "file_type": "code",
      "source_file": "src/pages/Home.jsx",
      "source_location": "L1",
      "id": "src_pages_home_jsx",
      "community": 7,
      "norm_label": "home.jsx"
    },
    {
      "label": "Home()",
      "file_type": "code",
      "source_file": "src/pages/Home.jsx",
      "source_location": "L9",
      "id": "pages_home_home",
      "community": 7,
      "norm_label": "home()"
    },
    {
      "label": "Reviews.jsx",
      "file_type": "code",
      "source_file": "src/pages/Reviews.jsx",
      "source_location": "L1",
      "id": "src_pages_reviews_jsx",
      "community": 1,
      "norm_label": "reviews.jsx"
    },
    {
      "label": "Reviews",
      "file_type": "code",
      "source_file": "src/pages/Reviews.jsx",
      "source_location": "L46",
      "id": "pages_reviews_reviews",
      "community": 1,
      "norm_label": "reviews"
    },
    {
      "label": "AppRoutes.jsx",
      "file_type": "code",
      "source_file": "src/routes/AppRoutes.jsx",
      "source_location": "L1",
      "id": "src_routes_approutes_jsx",
      "community": 1,
      "norm_label": "approutes.jsx"
    },
    {
      "label": "pageTransition",
      "file_type": "code",
      "source_file": "src/routes/AppRoutes.jsx",
      "source_location": "L12",
      "id": "routes_approutes_pagetransition",
      "community": 1,
      "norm_label": "pagetransition"
    },
    {
      "label": "PageWrapper()",
      "file_type": "code",
      "source_file": "src/routes/AppRoutes.jsx",
      "source_location": "L19",
      "id": "routes_approutes_pagewrapper",
      "community": 1,
      "norm_label": "pagewrapper()"
    },
    {
      "label": "AppRoutes()",
      "file_type": "code",
      "source_file": "src/routes/AppRoutes.jsx",
      "source_location": "L27",
      "id": "routes_approutes_approutes",
      "community": 1,
      "norm_label": "approutes()"
    },
    {
      "label": "ARCHITECTURE.md",
      "file_type": "document",
      "source_file": "ARCHITECTURE.md",
      "source_location": "L1",
      "id": "architecture_md",
      "community": 4,
      "norm_label": "architecture.md"
    },
    {
      "label": "Project Architecture - Ayswariya Mahal",
      "file_type": "document",
      "source_file": "ARCHITECTURE.md",
      "source_location": "L1",
      "id": "client_ayswariya_mahal_architecture_project_architecture_ayswariya_mahal",
      "community": 4,
      "norm_label": "project architecture - ayswariya mahal"
    },
    {
      "label": "\ud83d\udcc1 Directory Structure",
      "file_type": "document",
      "source_file": "ARCHITECTURE.md",
      "source_location": "L5",
      "id": "client_ayswariya_mahal_architecture_directory_structure",
      "community": 4,
      "norm_label": "\ud83d\udcc1 directory structure"
    },
    {
      "label": "code:text (src/)",
      "file_type": "document",
      "source_file": "ARCHITECTURE.md",
      "source_location": "L7",
      "id": "client_ayswariya_mahal_architecture_codeblock_1",
      "community": 4,
      "norm_label": "code:text (src/)"
    },
    {
      "label": "\ud83d\udd78\ufe0f Dependency Graph",
      "file_type": "document",
      "source_file": "ARCHITECTURE.md",
      "source_location": "L22",
      "id": "client_ayswariya_mahal_architecture_dependency_graph",
      "community": 4,
      "norm_label": "\ud83d\udd78\ufe0f dependency graph"
    },
    {
      "label": "code:mermaid (graph TD)",
      "file_type": "document",
      "source_file": "ARCHITECTURE.md",
      "source_location": "L24",
      "id": "client_ayswariya_mahal_architecture_codeblock_2",
      "community": 4,
      "norm_label": "code:mermaid (graph td)"
    },
    {
      "label": "\ud83d\udd17 Key Relationships & Rules",
      "file_type": "document",
      "source_file": "ARCHITECTURE.md",
      "source_location": "L60",
      "id": "client_ayswariya_mahal_architecture_key_relationships_rules",
      "community": 4,
      "norm_label": "\ud83d\udd17 key relationships & rules"
    },
    {
      "label": "\ud83d\uddfa\ufe0f Codebase Navigation Guide",
      "file_type": "document",
      "source_file": "ARCHITECTURE.md",
      "source_location": "L66",
      "id": "client_ayswariya_mahal_architecture_codebase_navigation_guide",
      "community": 4,
      "norm_label": "\ud83d\uddfa\ufe0f codebase navigation guide"
    },
    {
      "label": "README.md",
      "file_type": "document",
      "source_file": "README.md",
      "source_location": "L1",
      "id": "readme_md",
      "community": 6,
      "norm_label": "readme.md"
    },
    {
      "label": "Ayswariya Mahal - Royal Union Web Application \ud83c\udff0\u2728",
      "file_type": "document",
      "source_file": "README.md",
      "source_location": "L1",
      "id": "client_ayswariya_mahal_readme_ayswariya_mahal_royal_union_web_application",
      "community": 6,
      "norm_label": "ayswariya mahal - royal union web application \ud83c\udff0\u2728"
    },
    {
      "label": "\ud83d\ude80 Tech Stack",
      "file_type": "document",
      "source_file": "README.md",
      "source_location": "L9",
      "id": "client_ayswariya_mahal_readme_tech_stack",
      "community": 6,
      "norm_label": "\ud83d\ude80 tech stack"
    },
    {
      "label": "Core Architecture",
      "file_type": "document",
      "source_file": "README.md",
      "source_location": "L13",
      "id": "client_ayswariya_mahal_readme_core_architecture",
      "community": 6,
      "norm_label": "core architecture"
    },
    {
      "label": "Styling & UI",
      "file_type": "document",
      "source_file": "README.md",
      "source_location": "L18",
      "id": "client_ayswariya_mahal_readme_styling_ui",
      "community": 6,
      "norm_label": "styling & ui"
    },
    {
      "label": "Animation Engines",
      "file_type": "document",
      "source_file": "README.md",
      "source_location": "L22",
      "id": "client_ayswariya_mahal_readme_animation_engines",
      "community": 6,
      "norm_label": "animation engines"
    },
    {
      "label": "\ud83d\udcc2 Branching Strategy",
      "file_type": "document",
      "source_file": "README.md",
      "source_location": "L29",
      "id": "client_ayswariya_mahal_readme_branching_strategy",
      "community": 6,
      "norm_label": "\ud83d\udcc2 branching strategy"
    },
    {
      "label": "`main` Branch \ud83d\udfe2",
      "file_type": "document",
      "source_file": "README.md",
      "source_location": "L33",
      "id": "client_ayswariya_mahal_readme_main_branch",
      "community": 6,
      "norm_label": "`main` branch \ud83d\udfe2"
    },
    {
      "label": "`develop` Branch \ud83d\udfe1",
      "file_type": "document",
      "source_file": "README.md",
      "source_location": "L37",
      "id": "client_ayswariya_mahal_readme_develop_branch",
      "community": 6,
      "norm_label": "`develop` branch \ud83d\udfe1"
    },
    {
      "label": "Feature Branches \ud83d\udd35",
      "file_type": "document",
      "source_file": "README.md",
      "source_location": "L41",
      "id": "client_ayswariya_mahal_readme_feature_branches",
      "community": 6,
      "norm_label": "feature branches \ud83d\udd35"
    },
    {
      "label": "\ud83d\udee0\ufe0f Getting Started",
      "file_type": "document",
      "source_file": "README.md",
      "source_location": "L47",
      "id": "client_ayswariya_mahal_readme_getting_started",
      "community": 18,
      "norm_label": "\ud83d\udee0\ufe0f getting started"
    },
    {
      "label": "Prerequisites",
      "file_type": "document",
      "source_file": "README.md",
      "source_location": "L49",
      "id": "client_ayswariya_mahal_readme_prerequisites",
      "community": 18,
      "norm_label": "prerequisites"
    },
    {
      "label": "Installation",
      "file_type": "document",
      "source_file": "README.md",
      "source_location": "L52",
      "id": "client_ayswariya_mahal_readme_installation",
      "community": 18,
      "norm_label": "installation"
    },
    {
      "label": "code:bash (git clone [your-repo-url])",
      "file_type": "document",
      "source_file": "README.md",
      "source_location": "L54",
      "id": "client_ayswariya_mahal_readme_codeblock_1",
      "community": 18,
      "norm_label": "code:bash (git clone [your-repo-url])"
    },
    {
      "label": "code:bash (cd Client-Ayswariya-Mahal)",
      "file_type": "document",
      "source_file": "README.md",
      "source_location": "L58",
      "id": "client_ayswariya_mahal_readme_codeblock_2",
      "community": 18,
      "norm_label": "code:bash (cd client-ayswariya-mahal)"
    },
    {
      "label": "code:bash (npm install)",
      "file_type": "document",
      "source_file": "README.md",
      "source_location": "L62",
      "id": "client_ayswariya_mahal_readme_codeblock_3",
      "community": 18,
      "norm_label": "code:bash (npm install)"
    },
    {
      "label": "Running the Development Server",
      "file_type": "document",
      "source_file": "README.md",
      "source_location": "L66",
      "id": "client_ayswariya_mahal_readme_running_the_development_server",
      "community": 18,
      "norm_label": "running the development server"
    },
    {
      "label": "code:bash (npm run dev)",
      "file_type": "document",
      "source_file": "README.md",
      "source_location": "L68",
      "id": "client_ayswariya_mahal_readme_codeblock_4",
      "community": 18,
      "norm_label": "code:bash (npm run dev)"
    },
    {
      "label": "\ud83c\udfa8 Design Guidelines",
      "file_type": "document",
      "source_file": "README.md",
      "source_location": "L75",
      "id": "client_ayswariya_mahal_readme_design_guidelines",
      "community": 6,
      "norm_label": "\ud83c\udfa8 design guidelines"
    },
    {
      "label": "facilities",
      "file_type": "code",
      "source_file": "src/components/home/FacilitiesPreview.jsx",
      "source_location": "L15",
      "community": 0,
      "norm_label": "facilities",
      "id": "home_facilitiespreview_facilities"
    },
    {
      "label": "React + Vite",
      "file_type": "document",
      "source_file": "README.md",
      "source_location": "L1",
      "community": 6,
      "norm_label": "react + vite",
      "id": "client_ayswariya_mahal_readme_react_vite"
    },
    {
      "label": "React Compiler",
      "file_type": "document",
      "source_file": "README.md",
      "source_location": "L10",
      "community": 6,
      "norm_label": "react compiler",
      "id": "client_ayswariya_mahal_readme_react_compiler"
    },
    {
      "label": "Expanding the ESLint configuration",
      "file_type": "document",
      "source_file": "README.md",
      "source_location": "L14",
      "community": 6,
      "norm_label": "expanding the eslint configuration",
      "id": "client_ayswariya_mahal_readme_expanding_the_eslint_configuration"
    }
  ],
  "links": [
    {
      "relation": "contains",
      "confidence": "EXTRACTED",
      "source_file": "package.json",
      "source_location": "L12",
      "weight": 1.0,
      "confidence_score": 1.0,
      "source": "package_json",
      "target": "client_ayswariya_mahal_package_dependencies"
    },
    {
      "relation": "contains",
      "confidence": "EXTRACTED",
      "source_file": "package.json",
      "source_location": "L21",
      "weight": 1.0,
      "confidence_score": 1.0,
      "source": "package_json",
      "target": "client_ayswariya_mahal_package_devdependencies"
    },
    {
      "relation": "contains",
      "confidence": "EXTRACTED",
      "source_file": "package.json",
      "source_location": "L2",
      "weight": 1.0,
      "confidence_score": 1.0,
      "source": "package_json",
      "target": "client_ayswariya_mahal_package_name"
    },
    {
      "relation": "contains",
      "confidence": "EXTRACTED",
      "source_file": "package.json",
      "source_location": "L3",
      "weight": 1.0,
      "confidence_score": 1.0,
      "source": "package_json",
      "target": "client_ayswariya_mahal_package_private"
    },
    {
      "relation": "contains",
      "confidence": "EXTRACTED",
      "source_file": "package.json",
      "source_location": "L6",
      "weight": 1.0,
      "confidence_score": 1.0,
      "source": "package_json",
      "target": "client_ayswariya_mahal_package_scripts"
    },
    {
      "relation": "contains",
      "confidence": "EXTRACTED",
      "source_file": "package.json",
      "source_location": "L5",
      "weight": 1.0,
      "confidence_score": 1.0,
      "source": "package_json",
      "target": "client_ayswariya_mahal_package_type"
    },
    {
      "relation": "contains",
      "confidence": "EXTRACTED",
      "source_file": "package.json",
      "source_location": "L4",
      "weight": 1.0,
      "confidence_score": 1.0,
      "source": "package_json",
      "target": "client_ayswariya_mahal_package_version"
    },
    {
      "relation": "contains",
      "confidence": "EXTRACTED",
      "source_file": "package.json",
      "source_location": "L8",
      "weight": 1.0,
      "confidence_score": 1.0,
      "source": "client_ayswariya_mahal_package_scripts",
      "target": "client_ayswariya_mahal_package_scripts_build"
    },
    {
      "relation": "contains",
      "confidence": "EXTRACTED",
      "source_file": "package.json",
      "source_location": "L7",
      "weight": 1.0,
      "confidence_score": 1.0,
      "source": "client_ayswariya_mahal_package_scripts",
      "target": "client_ayswariya_mahal_package_scripts_dev"
    },
    {
      "relation": "contains",
      "confidence": "EXTRACTED",
      "source_file": "package.json",
      "source_location": "L9",
      "weight": 1.0,
      "confidence_score": 1.0,
      "source": "client_ayswariya_mahal_package_scripts",
      "target": "client_ayswariya_mahal_package_scripts_lint"
    },
    {
      "relation": "contains",
      "confidence": "EXTRACTED",
      "source_file": "package.json",
      "source_location": "L10",
      "weight": 1.0,
      "confidence_score": 1.0,
      "source": "client_ayswariya_mahal_package_scripts",
      "target": "client_ayswariya_mahal_package_scripts_preview"
    },
    {
      "relation": "contains",
      "confidence": "EXTRACTED",
      "source_file": "package.json",
      "source_location": "L13",
      "weight": 1.0,
      "confidence_score": 1.0,
      "source": "client_ayswariya_mahal_package_dependencies",
      "target": "client_ayswariya_mahal_package_dependencies_clsx"
    },
    {
      "relation": "contains",
      "confidence": "EXTRACTED",
      "source_file": "package.json",
      "source_location": "L14",
      "weight": 1.0,
      "confidence_score": 1.0,
      "source": "client_ayswariya_mahal_package_dependencies",
      "target": "client_ayswariya_mahal_package_dependencies_framer_motion"
    },
    {
      "relation": "contains",
      "confidence": "EXTRACTED",
      "source_file": "package.json",
      "source_location": "L15",
      "weight": 1.0,
      "confidence_score": 1.0,
      "source": "client_ayswariya_mahal_package_dependencies",
      "target": "client_ayswariya_mahal_package_dependencies_gsap"
    },
    {
      "relation": "contains",
      "confidence": "EXTRACTED",
      "source_file": "package.json",
      "source_location": "L16",
      "weight": 1.0,
      "confidence_score": 1.0,
      "source": "client_ayswariya_mahal_package_dependencies",
      "target": "client_ayswariya_mahal_package_dependencies_lucide_react"
    },
    {
      "relation": "contains",
      "confidence": "EXTRACTED",
      "source_file": "package.json",
      "source_location": "L17",
      "weight": 1.0,
      "confidence_score": 1.0,
      "source": "client_ayswariya_mahal_package_dependencies",
      "target": "client_ayswariya_mahal_package_dependencies_react"
    },
    {
      "relation": "contains",
      "confidence": "EXTRACTED",
      "source_file": "package.json",
      "source_location": "L18",
      "weight": 1.0,
      "confidence_score": 1.0,
      "source": "client_ayswariya_mahal_package_dependencies",
      "target": "client_ayswariya_mahal_package_dependencies_react_dom"
    },
    {
      "relation": "contains",
      "confidence": "EXTRACTED",
      "source_file": "package.json",
      "source_location": "L19",
      "weight": 1.0,
      "source": "client_ayswariya_mahal_package_dependencies",
      "target": "client_ayswariya_mahal_package_dependencies_react_helmet_async",
      "confidence_score": 1.0
    },
    {
      "relation": "contains",
      "confidence": "EXTRACTED",
      "source_file": "package.json",
      "source_location": "L19",
      "weight": 1.0,
      "confidence_score": 1.0,
      "source": "client_ayswariya_mahal_package_dependencies",
      "target": "client_ayswariya_mahal_package_dependencies_react_router_dom"
    },
    {
      "relation": "contains",
      "confidence": "EXTRACTED",
      "source_file": "package.json",
      "source_location": "L21",
      "weight": 1.0,
      "source": "client_ayswariya_mahal_package_dependencies",
      "target": "client_ayswariya_mahal_package_dependencies_sharp",
      "confidence_score": 1.0
    },
    {
      "relation": "contains",
      "confidence": "EXTRACTED",
      "source_file": "package.json",
      "source_location": "L27",
      "weight": 1.0,
      "confidence_score": 1.0,
      "source": "client_ayswariya_mahal_package_devdependencies",
      "target": "client_ayswariya_mahal_package_devdependencies_eslint"
    },
    {
      "relation": "contains",
      "confidence": "EXTRACTED",
      "source_file": "package.json",
      "source_location": "L22",
      "weight": 1.0,
      "confidence_score": 1.0,
      "source": "client_ayswariya_mahal_package_devdependencies",
      "target": "client_ayswariya_mahal_package_devdependencies_eslint_js"
    },
    {
      "relation": "contains",
      "confidence": "EXTRACTED",
      "source_file": "package.json",
      "source_location": "L28",
      "weight": 1.0,
      "confidence_score": 1.0,
      "source": "client_ayswariya_mahal_package_devdependencies",
      "target": "client_ayswariya_mahal_package_devdependencies_eslint_plugin_react_hooks"
    },
    {
      "relation": "contains",
      "confidence": "EXTRACTED",
      "source_file": "package.json",
      "source_location": "L29",
      "weight": 1.0,
      "confidence_score": 1.0,
      "source": "client_ayswariya_mahal_package_devdependencies",
      "target": "client_ayswariya_mahal_package_devdependencies_eslint_plugin_react_refresh"
    },
    {
      "relation": "contains",
      "confidence": "EXTRACTED",
      "source_file": "package.json",
      "source_location": "L30",
      "weight": 1.0,
      "confidence_score": 1.0,
      "source": "client_ayswariya_mahal_package_devdependencies",
      "target": "client_ayswariya_mahal_package_devdependencies_globals"
    },
    {
      "relation": "contains",
      "confidence": "EXTRACTED",
      "source_file": "package.json",
      "source_location": "L31",
      "weight": 1.0,
      "confidence_score": 1.0,
      "source": "client_ayswariya_mahal_package_devdependencies",
      "target": "client_ayswariya_mahal_package_devdependencies_tailwindcss"
    },
    {
      "relation": "contains",
      "confidence": "EXTRACTED",
      "source_file": "package.json",
      "source_location": "L23",
      "weight": 1.0,
      "confidence_score": 1.0,
      "source": "client_ayswariya_mahal_package_devdependencies",
      "target": "client_ayswariya_mahal_package_devdependencies_tailwindcss_vite"
    },
    {
      "relation": "contains",
      "confidence": "EXTRACTED",
      "source_file": "package.json",
      "source_location": "L24",
      "weight": 1.0,
      "confidence_score": 1.0,
      "source": "client_ayswariya_mahal_package_devdependencies",
      "target": "client_ayswariya_mahal_package_devdependencies_types_react"
    },
    {
      "relation": "contains",
      "confidence": "EXTRACTED",
      "source_file": "package.json",
      "source_location": "L25",
      "weight": 1.0,
      "confidence_score": 1.0,
      "source": "client_ayswariya_mahal_package_devdependencies",
      "target": "client_ayswariya_mahal_package_devdependencies_types_react_dom"
    },
    {
      "relation": "contains",
      "confidence": "EXTRACTED",
      "source_file": "package.json",
      "source_location": "L32",
      "weight": 1.0,
      "confidence_score": 1.0,
      "source": "client_ayswariya_mahal_package_devdependencies",
      "target": "client_ayswariya_mahal_package_devdependencies_vite"
    },
    {
      "relation": "contains",
      "confidence": "EXTRACTED",
      "source_file": "package.json",
      "source_location": "L26",
      "weight": 1.0,
      "confidence_score": 1.0,
      "source": "client_ayswariya_mahal_package_devdependencies",
      "target": "client_ayswariya_mahal_package_devdependencies_vitejs_plugin_react"
    },
    {
      "relation": "imports",
      "context": "import",
      "confidence": "EXTRACTED",
      "source_file": "src/App.jsx",
      "source_location": "L5",
      "weight": 1.0,
      "source": "src_app_jsx",
      "target": "context_enquirycontext_enquiryprovider",
      "confidence_score": 1.0
    },
    {
      "relation": "contains",
      "confidence": "EXTRACTED",
      "source_file": "src/App.jsx",
      "source_location": "L10",
      "weight": 1.0,
      "source": "src_app_jsx",
      "target": "src_app_about",
      "confidence_score": 1.0
    },
    {
      "relation": "contains",
      "confidence": "EXTRACTED",
      "source_file": "src/App.jsx",
      "source_location": "L4",
      "weight": 1.0,
      "confidence_score": 1.0,
      "source": "src_app_jsx",
      "target": "src_app_app"
    },
    {
      "relation": "contains",
      "confidence": "EXTRACTED",
      "source_file": "src/App.jsx",
      "source_location": "L13",
      "weight": 1.0,
      "source": "src_app_jsx",
      "target": "src_app_contact",
      "confidence_score": 1.0
    },
    {
      "relation": "contains",
      "confidence": "EXTRACTED",
      "source_file": "src/App.jsx",
      "source_location": "L11",
      "weight": 1.0,
      "source": "src_app_jsx",
      "target": "src_app_facilities",
      "confidence_score": 1.0
    },
    {
      "relation": "contains",
      "confidence": "EXTRACTED",
      "source_file": "src/App.jsx",
      "source_location": "L12",
      "weight": 1.0,
      "source": "src_app_jsx",
      "target": "src_app_gallery",
      "confidence_score": 1.0
    },
    {
      "relation": "contains",
      "confidence": "EXTRACTED",
      "source_file": "src/App.jsx",
      "source_location": "L9",
      "weight": 1.0,
      "source": "src_app_jsx",
      "target": "src_app_home",
      "confidence_score": 1.0
    },
    {
      "relation": "contains",
      "confidence": "EXTRACTED",
      "source_file": "src/App.jsx",
      "source_location": "L17",
      "weight": 1.0,
      "source": "src_app_jsx",
      "target": "src_app_pageloader",
      "confidence_score": 1.0
    },
    {
      "relation": "contains",
      "confidence": "EXTRACTED",
      "source_file": "src/App.jsx",
      "source_location": "L14",
      "weight": 1.0,
      "source": "src_app_jsx",
      "target": "src_app_reviews",
      "confidence_score": 1.0
    },
    {
      "relation": "imports_from",
      "context": "import",
      "confidence": "EXTRACTED",
      "source_file": "src/App.jsx",
      "source_location": "L6",
      "weight": 1.0,
      "source": "src_app_jsx",
      "target": "src_components_common_scrolltotop_jsx",
      "confidence_score": 1.0
    },
    {
      "relation": "imports_from",
      "context": "import",
      "confidence": "EXTRACTED",
      "source_file": "src/App.jsx",
      "source_location": "L5",
      "weight": 1.0,
      "source": "src_app_jsx",
      "target": "src_context_enquirycontext_jsx",
      "confidence_score": 1.0
    },
    {
      "relation": "imports_from",
      "context": "import",
      "confidence": "EXTRACTED",
      "source_file": "src/App.jsx",
      "source_location": "L4",
      "weight": 1.0,
      "source": "src_app_jsx",
      "target": "src_layouts_mainlayout_jsx",
      "confidence_score": 1.0
    },
    {
      "relation": "imports_from",
      "context": "import",
      "confidence": "EXTRACTED",
      "source_file": "src/App.jsx",
      "source_location": "L2",
      "weight": 1.0,
      "confidence_score": 1.0,
      "source": "src_app_jsx",
      "target": "src_routes_approutes_jsx"
    },
    {
      "relation": "imports_from",
      "context": "import",
      "confidence": "EXTRACTED",
      "source_file": "src/main.jsx",
      "source_location": "L4",
      "weight": 1.0,
      "confidence_score": 1.0,
      "source": "src_main_jsx",
      "target": "src_app_jsx"
    },
    {
      "relation": "contains",
      "confidence": "EXTRACTED",
      "source_file": "src/components/common/FloatingEnvelope.jsx",
      "source_location": "L17",
      "weight": 1.0,
      "confidence_score": 1.0,
      "source": "src_components_common_floatingenvelope_jsx",
      "target": "common_floatingenvelope_floatingenvelope"
    },
    {
      "relation": "contains",
      "confidence": "EXTRACTED",
      "source_file": "src/components/common/FloatingEnvelope.jsx",
      "source_location": "L6",
      "weight": 1.0,
      "confidence_score": 1.0,
      "source": "src_components_common_floatingenvelope_jsx",
      "target": "common_floatingenvelope_quotes"
    },
    {
      "relation": "imports",
      "context": "import",
      "confidence": "EXTRACTED",
      "source_file": "src/components/common/FloatingEnvelope.jsx",
      "source_location": "L4",
      "weight": 1.0,
      "confidence_score": 1.0,
      "source": "src_components_common_floatingenvelope_jsx",
      "target": "context_enquirycontext_useenquiry"
    },
    {
      "relation": "imports_from",
      "context": "import",
      "confidence": "EXTRACTED",
      "source_file": "src/components/common/FloatingEnvelope.jsx",
      "source_location": "L4",
      "weight": 1.0,
      "confidence_score": 1.0,
      "source": "src_components_common_floatingenvelope_jsx",
      "target": "src_context_enquirycontext_jsx"
    },
    {
      "relation": "imports_from",
      "context": "import",
      "confidence": "EXTRACTED",
      "source_file": "src/layouts/MainLayout.jsx",
      "source_location": "L3",
      "weight": 1.0,
      "confidence_score": 1.0,
      "source": "src_layouts_mainlayout_jsx",
      "target": "src_components_common_floatingenvelope_jsx"
    },
    {
      "relation": "calls",
      "context": "call",
      "confidence": "EXTRACTED",
      "confidence_score": 1.0,
      "source_file": "src/components/common/FloatingEnvelope.jsx",
      "source_location": "L18",
      "weight": 1.0,
      "source": "common_floatingenvelope_floatingenvelope",
      "target": "context_enquirycontext_useenquiry"
    },
    {
      "relation": "contains",
      "confidence": "EXTRACTED",
      "source_file": "src/components/common/Footer.jsx",
      "source_location": "L3",
      "weight": 1.0,
      "confidence_score": 1.0,
      "source": "src_components_common_footer_jsx",
      "target": "common_footer_footer"
    },
    {
      "relation": "imports_from",
      "context": "import",
      "confidence": "EXTRACTED",
      "source_file": "src/components/common/Footer.jsx",
      "source_location": "L3",
      "weight": 1.0,
      "source": "src_components_common_footer_jsx",
      "target": "src_config_site_js",
      "confidence_score": 1.0
    },
    {
      "relation": "imports_from",
      "context": "import",
      "confidence": "EXTRACTED",
      "source_file": "src/layouts/MainLayout.jsx",
      "source_location": "L2",
      "weight": 1.0,
      "confidence_score": 1.0,
      "source": "src_layouts_mainlayout_jsx",
      "target": "src_components_common_footer_jsx"
    },
    {
      "relation": "imports_from",
      "context": "import",
      "confidence": "EXTRACTED",
      "source_file": "src/pages/Home.jsx",
      "source_location": "L5",
      "weight": 1.0,
      "confidence_score": 1.0,
      "source": "src_pages_home_jsx",
      "target": "src_components_common_footer_jsx"
    },
    {
      "relation": "contains",
      "confidence": "EXTRACTED",
      "source_file": "src/components/common/Navbar.jsx",
      "source_location": "L5",
      "weight": 1.0,
      "confidence_score": 1.0,
      "source": "src_components_common_navbar_jsx",
      "target": "common_navbar_navbar"
    },
    {
      "relation": "imports",
      "context": "import",
      "confidence": "EXTRACTED",
      "source_file": "src/components/common/Navbar.jsx",
      "source_location": "L6",
      "weight": 1.0,
      "confidence_score": 1.0,
      "source": "src_components_common_navbar_jsx",
      "target": "context_enquirycontext_useenquiry"
    },
    {
      "relation": "imports_from",
      "context": "import",
      "confidence": "EXTRACTED",
      "source_file": "src/components/common/Navbar.jsx",
      "source_location": "L6",
      "weight": 1.0,
      "confidence_score": 1.0,
      "source": "src_components_common_navbar_jsx",
      "target": "src_context_enquirycontext_jsx"
    },
    {
      "relation": "imports_from",
      "context": "import",
      "confidence": "EXTRACTED",
      "source_file": "src/layouts/MainLayout.jsx",
      "source_location": "L1",
      "weight": 1.0,
      "confidence_score": 1.0,
      "source": "src_layouts_mainlayout_jsx",
      "target": "src_components_common_navbar_jsx"
    },
    {
      "relation": "imports_from",
      "context": "import",
      "confidence": "EXTRACTED",
      "source_file": "src/pages/Home.jsx",
      "source_location": "L1",
      "weight": 1.0,
      "confidence_score": 1.0,
      "source": "src_pages_home_jsx",
      "target": "src_components_common_navbar_jsx"
    },
    {
      "relation": "calls",
      "context": "call",
      "confidence": "EXTRACTED",
      "source_file": "src/components/common/Navbar.jsx",
      "source_location": "L11",
      "weight": 1.0,
      "confidence_score": 1.0,
      "source": "common_navbar_navbar",
      "target": "context_enquirycontext_useenquiry"
    },
    {
      "relation": "contains",
      "confidence": "EXTRACTED",
      "source_file": "src/components/common/ScrollToTop.jsx",
      "source_location": "L4",
      "weight": 1.0,
      "source": "src_components_common_scrolltotop_jsx",
      "target": "common_scrolltotop_scrolltotop",
      "confidence_score": 1.0
    },
    {
      "relation": "contains",
      "confidence": "EXTRACTED",
      "source_file": "src/components/common/SEO.jsx",
      "source_location": "L4",
      "weight": 1.0,
      "source": "src_components_common_seo_jsx",
      "target": "common_seo_seo",
      "confidence_score": 1.0
    },
    {
      "relation": "imports_from",
      "context": "import",
      "confidence": "EXTRACTED",
      "source_file": "src/components/common/SEO.jsx",
      "source_location": "L2",
      "weight": 1.0,
      "source": "src_components_common_seo_jsx",
      "target": "src_config_site_js",
      "confidence_score": 1.0
    },
    {
      "relation": "imports_from",
      "context": "import",
      "confidence": "EXTRACTED",
      "source_file": "src/pages/About.jsx",
      "source_location": "L6",
      "weight": 1.0,
      "source": "src_pages_about_jsx",
      "target": "src_components_common_seo_jsx",
      "confidence_score": 1.0
    },
    {
      "relation": "imports_from",
      "context": "import",
      "confidence": "EXTRACTED",
      "source_file": "src/pages/Contact.jsx",
      "source_location": "L5",
      "weight": 1.0,
      "source": "src_pages_contact_jsx",
      "target": "src_components_common_seo_jsx",
      "confidence_score": 1.0
    },
    {
      "relation": "imports_from",
      "context": "import",
      "confidence": "EXTRACTED",
      "source_file": "src/pages/Facilities.jsx",
      "source_location": "L15",
      "weight": 1.0,
      "source": "src_pages_facilities_jsx",
      "target": "src_components_common_seo_jsx",
      "confidence_score": 1.0
    },
    {
      "relation": "imports_from",
      "context": "import",
      "confidence": "EXTRACTED",
      "source_file": "src/pages/Gallery.jsx",
      "source_location": "L10",
      "weight": 1.0,
      "source": "src_pages_gallery_jsx",
      "target": "src_components_common_seo_jsx",
      "confidence_score": 1.0
    },
    {
      "relation": "imports_from",
      "context": "import",
      "confidence": "EXTRACTED",
      "source_file": "src/pages/Home.jsx",
      "source_location": "L7",
      "weight": 1.0,
      "source": "src_pages_home_jsx",
      "target": "src_components_common_seo_jsx",
      "confidence_score": 1.0
    },
    {
      "relation": "imports_from",
      "context": "import",
      "confidence": "EXTRACTED",
      "source_file": "src/pages/Reviews.jsx",
      "source_location": "L5",
      "weight": 1.0,
      "source": "src_pages_reviews_jsx",
      "target": "src_components_common_seo_jsx",
      "confidence_score": 1.0
    },
    {
      "relation": "contains",
      "confidence": "EXTRACTED",
      "source_file": "src/components/home/AboutPreview.jsx",
      "source_location": "L9",
      "weight": 1.0,
      "confidence_score": 1.0,
      "source": "src_components_home_aboutpreview_jsx",
      "target": "home_aboutpreview_aboutpreview"
    },
    {
      "relation": "imports_from",
      "context": "import",
      "confidence": "EXTRACTED",
      "source_file": "src/pages/Home.jsx",
      "source_location": "L3",
      "weight": 1.0,
      "confidence_score": 1.0,
      "source": "src_pages_home_jsx",
      "target": "src_components_home_aboutpreview_jsx"
    },
    {
      "relation": "imports",
      "context": "import",
      "confidence": "EXTRACTED",
      "source_file": "src/components/home/ContactCTA.jsx",
      "source_location": "L2",
      "weight": 1.0,
      "source": "src_components_home_contactcta_jsx",
      "target": "context_enquirycontext_useenquiry",
      "confidence_score": 1.0
    },
    {
      "relation": "contains",
      "confidence": "EXTRACTED",
      "source_file": "src/components/home/ContactCTA.jsx",
      "source_location": "L4",
      "weight": 1.0,
      "source": "src_components_home_contactcta_jsx",
      "target": "home_contactcta_contactcta",
      "confidence_score": 1.0
    },
    {
      "relation": "imports_from",
      "context": "import",
      "confidence": "EXTRACTED",
      "source_file": "src/components/home/ContactCTA.jsx",
      "source_location": "L2",
      "weight": 1.0,
      "source": "src_components_home_contactcta_jsx",
      "target": "src_context_enquirycontext_jsx",
      "confidence_score": 1.0
    },
    {
      "relation": "imports_from",
      "context": "import",
      "confidence": "EXTRACTED",
      "source_file": "src/pages/Home.jsx",
      "source_location": "L6",
      "weight": 1.0,
      "source": "src_pages_home_jsx",
      "target": "src_components_home_contactcta_jsx",
      "confidence_score": 1.0
    },
    {
      "relation": "calls",
      "context": "call",
      "confidence": "EXTRACTED",
      "confidence_score": 1.0,
      "source_file": "src/components/home/ContactCTA.jsx",
      "source_location": "L5",
      "weight": 1.0,
      "source": "home_contactcta_contactcta",
      "target": "context_enquirycontext_useenquiry"
    },
    {
      "relation": "contains",
      "confidence": "EXTRACTED",
      "source_file": "src/components/home/FacilitiesPreview.jsx",
      "source_location": "L15",
      "weight": 1.0,
      "confidence_score": 1.0,
      "source": "src_components_home_facilitiespreview_jsx",
      "target": "home_facilitiespreview_facilities"
    },
    {
      "relation": "contains",
      "confidence": "EXTRACTED",
      "source_file": "src/components/home/FacilitiesPreview.jsx",
      "source_location": "L38",
      "weight": 1.0,
      "confidence_score": 1.0,
      "source": "src_components_home_facilitiespreview_jsx",
      "target": "home_facilitiespreview_facilitiespreview"
    },
    {
      "relation": "contains",
      "confidence": "EXTRACTED",
      "source_file": "src/components/home/FacilitiesPreview.jsx",
      "source_location": "L14",
      "weight": 1.0,
      "source": "src_components_home_facilitiespreview_jsx",
      "target": "home_facilitiespreview_images",
      "confidence_score": 1.0
    },
    {
      "relation": "imports_from",
      "context": "import",
      "confidence": "EXTRACTED",
      "source_file": "src/pages/Home.jsx",
      "source_location": "L4",
      "weight": 1.0,
      "confidence_score": 1.0,
      "source": "src_pages_home_jsx",
      "target": "src_components_home_facilitiespreview_jsx"
    },
    {
      "relation": "contains",
      "confidence": "EXTRACTED",
      "source_file": "src/components/home/GalleryPreview.jsx",
      "source_location": "L9",
      "weight": 1.0,
      "source": "src_components_home_gallerypreview_jsx",
      "target": "home_gallerypreview_gallerypreview",
      "confidence_score": 1.0
    },
    {
      "relation": "imports_from",
      "context": "import",
      "confidence": "EXTRACTED",
      "source_file": "src/pages/Home.jsx",
      "source_location": "L5",
      "weight": 1.0,
      "source": "src_pages_home_jsx",
      "target": "src_components_home_gallerypreview_jsx",
      "confidence_score": 1.0
    },
    {
      "relation": "contains",
      "confidence": "EXTRACTED",
      "source_file": "src/components/home/GateExperience.jsx",
      "source_location": "L10",
      "weight": 1.0,
      "confidence_score": 1.0,
      "source": "src_components_home_gateexperience_jsx",
      "target": "home_gateexperience_gateexperience"
    },
    {
      "relation": "imports_from",
      "context": "import",
      "confidence": "EXTRACTED",
      "source_file": "src/pages/Home.jsx",
      "source_location": "L2",
      "weight": 1.0,
      "confidence_score": 1.0,
      "source": "src_pages_home_jsx",
      "target": "src_components_home_gateexperience_jsx"
    },
    {
      "relation": "contains",
      "confidence": "EXTRACTED",
      "source_file": "src/components/home/Hero.jsx",
      "source_location": "L6",
      "weight": 1.0,
      "confidence_score": 1.0,
      "source": "src_components_home_hero_jsx",
      "target": "home_hero_hero"
    },
    {
      "relation": "contains",
      "confidence": "EXTRACTED",
      "source_file": "src/components/home/RoyalStatistics.jsx",
      "source_location": "L4",
      "weight": 1.0,
      "source": "src_components_home_royalstatistics_jsx",
      "target": "home_royalstatistics_royalstatistics",
      "confidence_score": 1.0
    },
    {
      "relation": "imports_from",
      "context": "import",
      "confidence": "EXTRACTED",
      "source_file": "src/pages/Home.jsx",
      "source_location": "L3",
      "weight": 1.0,
      "source": "src_pages_home_jsx",
      "target": "src_components_home_royalstatistics_jsx",
      "confidence_score": 1.0
    },
    {
      "relation": "contains",
      "confidence": "EXTRACTED",
      "source_file": "src/config/site.js",
      "source_location": "L1",
      "weight": 1.0,
      "source": "src_config_site_js",
      "target": "config_site_siteconfig",
      "confidence_score": 1.0
    },
    {
      "relation": "contains",
      "confidence": "EXTRACTED",
      "source_file": "src/context/EnquiryContext.jsx",
      "source_location": "L3",
      "weight": 1.0,
      "confidence_score": 1.0,
      "source": "src_context_enquirycontext_jsx",
      "target": "context_enquirycontext_enquirycontext"
    },
    {
      "relation": "contains",
      "confidence": "EXTRACTED",
      "source_file": "src/context/EnquiryContext.jsx",
      "source_location": "L7",
      "weight": 1.0,
      "confidence_score": 1.0,
      "source": "src_context_enquirycontext_jsx",
      "target": "context_enquirycontext_enquiryprovider"
    },
    {
      "relation": "contains",
      "confidence": "EXTRACTED",
      "source_file": "src/context/EnquiryContext.jsx",
      "source_location": "L5",
      "weight": 1.0,
      "confidence_score": 1.0,
      "source": "src_context_enquirycontext_jsx",
      "target": "context_enquirycontext_useenquiry"
    },
    {
      "relation": "imports_from",
      "context": "import",
      "confidence": "EXTRACTED",
      "source_file": "src/layouts/MainLayout.jsx",
      "source_location": "L4",
      "weight": 1.0,
      "confidence_score": 1.0,
      "source": "src_layouts_mainlayout_jsx",
      "target": "src_context_enquirycontext_jsx"
    },
    {
      "relation": "imports_from",
      "context": "import",
      "confidence": "EXTRACTED",
      "source_file": "src/pages/Contact.jsx",
      "source_location": "L3",
      "weight": 1.0,
      "source": "src_pages_contact_jsx",
      "target": "src_context_enquirycontext_jsx",
      "confidence_score": 1.0
    },
    {
      "relation": "imports_from",
      "context": "import",
      "confidence": "EXTRACTED",
      "source_file": "src/pages/Reviews.jsx",
      "source_location": "L3",
      "weight": 1.0,
      "source": "src_pages_reviews_jsx",
      "target": "src_context_enquirycontext_jsx",
      "confidence_score": 1.0
    },
    {
      "relation": "calls",
      "context": "call",
      "confidence": "EXTRACTED",
      "confidence_score": 1.0,
      "source_file": "src/pages/Contact.jsx",
      "source_location": "L8",
      "weight": 1.0,
      "source": "pages_contact_contact",
      "target": "context_enquirycontext_useenquiry"
    },
    {
      "relation": "calls",
      "context": "call",
      "confidence": "EXTRACTED",
      "confidence_score": 1.0,
      "source_file": "src/pages/Reviews.jsx",
      "source_location": "L47",
      "weight": 1.0,
      "source": "pages_reviews_reviews",
      "target": "context_enquirycontext_useenquiry"
    },
    {
      "relation": "imports",
      "context": "import",
      "confidence": "EXTRACTED",
      "source_file": "src/pages/Contact.jsx",
      "source_location": "L3",
      "weight": 1.0,
      "source": "src_pages_contact_jsx",
      "target": "context_enquirycontext_useenquiry",
      "confidence_score": 1.0
    },
    {
      "relation": "imports",
      "context": "import",
      "confidence": "EXTRACTED",
      "source_file": "src/pages/Reviews.jsx",
      "source_location": "L3",
      "weight": 1.0,
      "source": "src_pages_reviews_jsx",
      "target": "context_enquirycontext_useenquiry",
      "confidence_score": 1.0
    },
    {
      "relation": "imports",
      "context": "import",
      "confidence": "EXTRACTED",
      "source_file": "src/layouts/MainLayout.jsx",
      "source_location": "L4",
      "weight": 1.0,
      "confidence_score": 1.0,
      "source": "src_layouts_mainlayout_jsx",
      "target": "context_enquirycontext_enquiryprovider"
    },
    {
      "relation": "contains",
      "confidence": "EXTRACTED",
      "source_file": "src/layouts/MainLayout.jsx",
      "source_location": "L4",
      "weight": 1.0,
      "confidence_score": 1.0,
      "source": "src_layouts_mainlayout_jsx",
      "target": "layouts_mainlayout_mainlayout"
    },
    {
      "relation": "imports_from",
      "context": "import",
      "confidence": "EXTRACTED",
      "source_file": "src/routes/AppRoutes.jsx",
      "source_location": "L3",
      "weight": 1.0,
      "confidence_score": 1.0,
      "source": "src_routes_approutes_jsx",
      "target": "src_layouts_mainlayout_jsx"
    },
    {
      "relation": "contains",
      "confidence": "EXTRACTED",
      "source_file": "src/pages/About.jsx",
      "source_location": "L3",
      "weight": 1.0,
      "confidence_score": 1.0,
      "source": "src_pages_about_jsx",
      "target": "pages_about_about"
    },
    {
      "relation": "imports_from",
      "context": "import",
      "confidence": "EXTRACTED",
      "source_file": "src/routes/AppRoutes.jsx",
      "source_location": "L9",
      "weight": 1.0,
      "confidence_score": 1.0,
      "source": "src_routes_approutes_jsx",
      "target": "src_pages_about_jsx"
    },
    {
      "relation": "contains",
      "confidence": "EXTRACTED",
      "source_file": "src/pages/Contact.jsx",
      "source_location": "L7",
      "weight": 1.0,
      "source": "src_pages_contact_jsx",
      "target": "pages_contact_contact",
      "confidence_score": 1.0
    },
    {
      "relation": "imports_from",
      "context": "import",
      "confidence": "EXTRACTED",
      "source_file": "src/routes/AppRoutes.jsx",
      "source_location": "L10",
      "weight": 1.0,
      "source": "src_routes_approutes_jsx",
      "target": "src_pages_contact_jsx",
      "confidence_score": 1.0
    },
    {
      "relation": "contains",
      "confidence": "EXTRACTED",
      "source_file": "src/pages/Facilities.jsx",
      "source_location": "L64",
      "weight": 1.0,
      "confidence_score": 1.0,
      "source": "src_pages_facilities_jsx",
      "target": "pages_facilities_facilities"
    },
    {
      "relation": "imports_from",
      "context": "import",
      "confidence": "EXTRACTED",
      "source_file": "src/routes/AppRoutes.jsx",
      "source_location": "L10",
      "weight": 1.0,
      "confidence_score": 1.0,
      "source": "src_routes_approutes_jsx",
      "target": "src_pages_facilities_jsx"
    },
    {
      "relation": "contains",
      "confidence": "EXTRACTED",
      "source_file": "src/pages/Gallery.jsx",
      "source_location": "L19",
      "weight": 1.0,
      "confidence_score": 1.0,
      "source": "src_pages_gallery_jsx",
      "target": "pages_gallery_categories"
    },
    {
      "relation": "contains",
      "confidence": "EXTRACTED",
      "source_file": "src/pages/Gallery.jsx",
      "source_location": "L21",
      "weight": 1.0,
      "confidence_score": 1.0,
      "source": "src_pages_gallery_jsx",
      "target": "pages_gallery_gallery"
    },
    {
      "relation": "contains",
      "confidence": "EXTRACTED",
      "source_file": "src/pages/Gallery.jsx",
      "source_location": "L10",
      "weight": 1.0,
      "confidence_score": 1.0,
      "source": "src_pages_gallery_jsx",
      "target": "pages_gallery_galleryimages"
    },
    {
      "relation": "imports_from",
      "context": "import",
      "confidence": "EXTRACTED",
      "source_file": "src/routes/AppRoutes.jsx",
      "source_location": "L7",
      "weight": 1.0,
      "confidence_score": 1.0,
      "source": "src_routes_approutes_jsx",
      "target": "src_pages_gallery_jsx"
    },
    {
      "relation": "contains",
      "confidence": "EXTRACTED",
      "source_file": "src/pages/Home.jsx",
      "source_location": "L7",
      "weight": 1.0,
      "confidence_score": 1.0,
      "source": "src_pages_home_jsx",
      "target": "pages_home_home"
    },
    {
      "relation": "imports_from",
      "context": "import",
      "confidence": "EXTRACTED",
      "source_file": "src/routes/AppRoutes.jsx",
      "source_location": "L5",
      "weight": 1.0,
      "confidence_score": 1.0,
      "source": "src_routes_approutes_jsx",
      "target": "src_pages_home_jsx"
    },
    {
      "relation": "contains",
      "confidence": "EXTRACTED",
      "source_file": "src/pages/Reviews.jsx",
      "source_location": "L43",
      "weight": 1.0,
      "confidence_score": 1.0,
      "source": "src_pages_reviews_jsx",
      "target": "pages_reviews_reviews"
    },
    {
      "relation": "imports_from",
      "context": "import",
      "confidence": "EXTRACTED",
      "source_file": "src/routes/AppRoutes.jsx",
      "source_location": "L8",
      "weight": 1.0,
      "confidence_score": 1.0,
      "source": "src_routes_approutes_jsx",
      "target": "src_pages_reviews_jsx"
    },
    {
      "relation": "contains",
      "confidence": "EXTRACTED",
      "source_file": "src/routes/AppRoutes.jsx",
      "source_location": "L25",
      "weight": 1.0,
      "confidence_score": 1.0,
      "source": "src_routes_approutes_jsx",
      "target": "routes_approutes_approutes"
    },
    {
      "relation": "contains",
      "confidence": "EXTRACTED",
      "source_file": "src/routes/AppRoutes.jsx",
      "source_location": "L12",
      "weight": 1.0,
      "confidence_score": 1.0,
      "source": "src_routes_approutes_jsx",
      "target": "routes_approutes_pagetransition"
    },
    {
      "relation": "contains",
      "confidence": "EXTRACTED",
      "source_file": "src/routes/AppRoutes.jsx",
      "source_location": "L19",
      "weight": 1.0,
      "confidence_score": 1.0,
      "source": "src_routes_approutes_jsx",
      "target": "routes_approutes_pagewrapper"
    },
    {
      "relation": "contains",
      "confidence": "EXTRACTED",
      "source_file": "ARCHITECTURE.md",
      "source_location": "L1",
      "weight": 1.0,
      "confidence_score": 1.0,
      "source": "architecture_md",
      "target": "client_ayswariya_mahal_architecture_project_architecture_ayswariya_mahal"
    },
    {
      "relation": "contains",
      "confidence": "EXTRACTED",
      "source_file": "ARCHITECTURE.md",
      "source_location": "L66",
      "weight": 1.0,
      "confidence_score": 1.0,
      "source": "client_ayswariya_mahal_architecture_project_architecture_ayswariya_mahal",
      "target": "client_ayswariya_mahal_architecture_codebase_navigation_guide"
    },
    {
      "relation": "contains",
      "confidence": "EXTRACTED",
      "source_file": "ARCHITECTURE.md",
      "source_location": "L22",
      "weight": 1.0,
      "confidence_score": 1.0,
      "source": "client_ayswariya_mahal_architecture_project_architecture_ayswariya_mahal",
      "target": "client_ayswariya_mahal_architecture_dependency_graph"
    },
    {
      "relation": "contains",
      "confidence": "EXTRACTED",
      "source_file": "ARCHITECTURE.md",
      "source_location": "L5",
      "weight": 1.0,
      "confidence_score": 1.0,
      "source": "client_ayswariya_mahal_architecture_project_architecture_ayswariya_mahal",
      "target": "client_ayswariya_mahal_architecture_directory_structure"
    },
    {
      "relation": "contains",
      "confidence": "EXTRACTED",
      "source_file": "ARCHITECTURE.md",
      "source_location": "L60",
      "weight": 1.0,
      "confidence_score": 1.0,
      "source": "client_ayswariya_mahal_architecture_project_architecture_ayswariya_mahal",
      "target": "client_ayswariya_mahal_architecture_key_relationships_rules"
    },
    {
      "relation": "contains",
      "confidence": "EXTRACTED",
      "source_file": "ARCHITECTURE.md",
      "source_location": "L7",
      "weight": 1.0,
      "confidence_score": 1.0,
      "source": "client_ayswariya_mahal_architecture_directory_structure",
      "target": "client_ayswariya_mahal_architecture_codeblock_1"
    },
    {
      "relation": "contains",
      "confidence": "EXTRACTED",
      "source_file": "ARCHITECTURE.md",
      "source_location": "L24",
      "weight": 1.0,
      "confidence_score": 1.0,
      "source": "client_ayswariya_mahal_architecture_dependency_graph",
      "target": "client_ayswariya_mahal_architecture_codeblock_2"
    },
    {
      "relation": "contains",
      "confidence": "EXTRACTED",
      "source_file": "README.md",
      "source_location": "L1",
      "weight": 1.0,
      "confidence_score": 1.0,
      "source": "readme_md",
      "target": "client_ayswariya_mahal_readme_ayswariya_mahal_royal_union_web_application"
    },
    {
      "relation": "contains",
      "confidence": "EXTRACTED",
      "source_file": "README.md",
      "source_location": "L1",
      "weight": 1.0,
      "confidence_score": 1.0,
      "source": "readme_md",
      "target": "client_ayswariya_mahal_readme_react_vite"
    },
    {
      "relation": "contains",
      "confidence": "EXTRACTED",
      "source_file": "README.md",
      "source_location": "L29",
      "weight": 1.0,
      "confidence_score": 1.0,
      "source": "client_ayswariya_mahal_readme_ayswariya_mahal_royal_union_web_application",
      "target": "client_ayswariya_mahal_readme_branching_strategy"
    },
    {
      "relation": "contains",
      "confidence": "EXTRACTED",
      "source_file": "README.md",
      "source_location": "L75",
      "weight": 1.0,
      "confidence_score": 1.0,
      "source": "client_ayswariya_mahal_readme_ayswariya_mahal_royal_union_web_application",
      "target": "client_ayswariya_mahal_readme_design_guidelines"
    },
    {
      "relation": "contains",
      "confidence": "EXTRACTED",
      "source_file": "README.md",
      "source_location": "L47",
      "weight": 1.0,
      "confidence_score": 1.0,
      "source": "client_ayswariya_mahal_readme_ayswariya_mahal_royal_union_web_application",
      "target": "client_ayswariya_mahal_readme_getting_started"
    },
    {
      "relation": "contains",
      "confidence": "EXTRACTED",
      "source_file": "README.md",
      "source_location": "L9",
      "weight": 1.0,
      "confidence_score": 1.0,
      "source": "client_ayswariya_mahal_readme_ayswariya_mahal_royal_union_web_application",
      "target": "client_ayswariya_mahal_readme_tech_stack"
    },
    {
      "relation": "contains",
      "confidence": "EXTRACTED",
      "source_file": "README.md",
      "source_location": "L22",
      "weight": 1.0,
      "confidence_score": 1.0,
      "source": "client_ayswariya_mahal_readme_tech_stack",
      "target": "client_ayswariya_mahal_readme_animation_engines"
    },
    {
      "relation": "contains",
      "confidence": "EXTRACTED",
      "source_file": "README.md",
      "source_location": "L13",
      "weight": 1.0,
      "confidence_score": 1.0,
      "source": "client_ayswariya_mahal_readme_tech_stack",
      "target": "client_ayswariya_mahal_readme_core_architecture"
    },
    {
      "relation": "contains",
      "confidence": "EXTRACTED",
      "source_file": "README.md",
      "source_location": "L18",
      "weight": 1.0,
      "confidence_score": 1.0,
      "source": "client_ayswariya_mahal_readme_tech_stack",
      "target": "client_ayswariya_mahal_readme_styling_ui"
    },
    {
      "relation": "contains",
      "confidence": "EXTRACTED",
      "source_file": "README.md",
      "source_location": "L37",
      "weight": 1.0,
      "confidence_score": 1.0,
      "source": "client_ayswariya_mahal_readme_branching_strategy",
      "target": "client_ayswariya_mahal_readme_develop_branch"
    },
    {
      "relation": "contains",
      "confidence": "EXTRACTED",
      "source_file": "README.md",
      "source_location": "L41",
      "weight": 1.0,
      "confidence_score": 1.0,
      "source": "client_ayswariya_mahal_readme_branching_strategy",
      "target": "client_ayswariya_mahal_readme_feature_branches"
    },
    {
      "relation": "contains",
      "confidence": "EXTRACTED",
      "source_file": "README.md",
      "source_location": "L33",
      "weight": 1.0,
      "confidence_score": 1.0,
      "source": "client_ayswariya_mahal_readme_branching_strategy",
      "target": "client_ayswariya_mahal_readme_main_branch"
    },
    {
      "relation": "contains",
      "confidence": "EXTRACTED",
      "source_file": "README.md",
      "source_location": "L52",
      "weight": 1.0,
      "confidence_score": 1.0,
      "source": "client_ayswariya_mahal_readme_getting_started",
      "target": "client_ayswariya_mahal_readme_installation"
    },
    {
      "relation": "contains",
      "confidence": "EXTRACTED",
      "source_file": "README.md",
      "source_location": "L49",
      "weight": 1.0,
      "confidence_score": 1.0,
      "source": "client_ayswariya_mahal_readme_getting_started",
      "target": "client_ayswariya_mahal_readme_prerequisites"
    },
    {
      "relation": "contains",
      "confidence": "EXTRACTED",
      "source_file": "README.md",
      "source_location": "L66",
      "weight": 1.0,
      "confidence_score": 1.0,
      "source": "client_ayswariya_mahal_readme_getting_started",
      "target": "client_ayswariya_mahal_readme_running_the_development_server"
    },
    {
      "relation": "contains",
      "confidence": "EXTRACTED",
      "source_file": "README.md",
      "source_location": "L54",
      "weight": 1.0,
      "confidence_score": 1.0,
      "source": "client_ayswariya_mahal_readme_installation",
      "target": "client_ayswariya_mahal_readme_codeblock_1"
    },
    {
      "relation": "contains",
      "confidence": "EXTRACTED",
      "source_file": "README.md",
      "source_location": "L58",
      "weight": 1.0,
      "confidence_score": 1.0,
      "source": "client_ayswariya_mahal_readme_installation",
      "target": "client_ayswariya_mahal_readme_codeblock_2"
    },
    {
      "relation": "contains",
      "confidence": "EXTRACTED",
      "source_file": "README.md",
      "source_location": "L62",
      "weight": 1.0,
      "confidence_score": 1.0,
      "source": "client_ayswariya_mahal_readme_installation",
      "target": "client_ayswariya_mahal_readme_codeblock_3"
    },
    {
      "relation": "contains",
      "confidence": "EXTRACTED",
      "source_file": "README.md",
      "source_location": "L68",
      "weight": 1.0,
      "confidence_score": 1.0,
      "source": "client_ayswariya_mahal_readme_running_the_development_server",
      "target": "client_ayswariya_mahal_readme_codeblock_4"
    },
    {
      "relation": "contains",
      "confidence": "EXTRACTED",
      "source_file": "README.md",
      "source_location": "L14",
      "weight": 1.0,
      "confidence_score": 1.0,
      "source": "client_ayswariya_mahal_readme_react_vite",
      "target": "client_ayswariya_mahal_readme_expanding_the_eslint_configuration"
    },
    {
      "relation": "contains",
      "confidence": "EXTRACTED",
      "source_file": "README.md",
      "source_location": "L10",
      "weight": 1.0,
      "confidence_score": 1.0,
      "source": "client_ayswariya_mahal_readme_react_vite",
      "target": "client_ayswariya_mahal_readme_react_compiler"
    }
  ],
  "hyperedges": [],
  "built_at_commit": "2858f730a2dbcf4367d79f6b087706d419995b95"
}